{
  "content": [],
  "elements": [
    {
      "Stave": {
        "char_index": 0,
        "column": 1,
        "index_in_doc": 0,
        "index_in_line": 0,
        "line": 1,
        "lines": [
          {
            "ContentLine": {
              "char_index": 0,
              "consumed_elements": [],
              "elements": [
                {
                  "Beat": {
                    "char_index": 0,
                    "consumed_elements": [],
                    "divisions": null,
                    "elements": [
                      {
                        "Note": {
                          "char_index": 0,
                          "consumed_elements": [],
                          "denominator": null,
                          "id": "9f33f651-e2c8-48df-af65-048ee2056e0b",
                          "notation_system": "Sargam",
                          "numerator": null,
                          "octave": 0,
                          "pitch_code": "N1",
                          "value": "S"
                        }
                      }
                    ],
                    "id": "4bf4f17a-f620-462c-bd3e-c10059753cdc",
                    "is_tuplet": null,
                    "tied_to_previous": null,
                    "total_duration": null,
                    "tuplet_ratio": null,
                    "value": null
                  }
                },
                {
                  "Whitespace": {
                    "char_index": 1,
                    "consumed_elements": [],
                    "id": "670b882e-be91-4873-af1d-e11d8f4f4d37",
                    "value": " "
                  }
                },
                {
                  "Beat": {
                    "char_index": 2,
                    "consumed_elements": [],
                    "divisions": null,
                    "elements": [
                      {
                        "Note": {
                          "char_index": 2,
                          "consumed_elements": [],
                          "denominator": null,
                          "id": "ed9bd629-6ada-46c6-89f7-d850140a84a8",
                          "notation_system": "Sargam",
                          "numerator": null,
                          "octave": 0,
                          "pitch_code": "N2",
                          "value": "R"
                        }
                      }
                    ],
                    "id": "c1d39c0d-cd51-41d3-9d40-e082d32d3068",
                    "is_tuplet": null,
                    "tied_to_previous": null,
                    "total_duration": null,
                    "tuplet_ratio": null,
                    "value": null
                  }
                },
                {
                  "Whitespace": {
                    "char_index": 3,
                    "consumed_elements": [],
                    "id": "148b7e55-09c7-4ffb-af55-8930c91ecd3d",
                    "value": " "
                  }
                },
                {
                  "Beat": {
                    "char_index": 4,
                    "consumed_elements": [],
                    "divisions": null,
                    "elements": [
                      {
                        "Note": {
                          "char_index": 4,
                          "consumed_elements": [],
                          "denominator": null,
                          "id": "a03346d4-3d32-4178-b558-e513d0224d1f",
                          "notation_system": "Sargam",
                          "numerator": null,
                          "octave": 0,
                          "pitch_code": "N3",
                          "value": "G"
                        }
                      }
                    ],
                    "id": "c013a4eb-a237-492e-a5d2-f84fd157cae8",
                    "is_tuplet": null,
                    "tied_to_previous": null,
                    "total_duration": null,
                    "tuplet_ratio": null,
                    "value": null
                  }
                },
                {
                  "Whitespace": {
                    "char_index": 5,
                    "consumed_elements": [],
                    "id": "817bf723-6fae-467d-830a-f25ca6c28442",
                    "value": " "
                  }
                },
                {
                  "Beat": {
                    "char_index": 6,
                    "consumed_elements": [],
                    "divisions": null,
                    "elements": [
                      {
                        "Note": {
                          "char_index": 6,
                          "consumed_elements": [],
                          "denominator": null,
                          "id": "28f9c887-2651-4a8f-8b68-7e7b57366109",
                          "notation_system": "Sargam",
                          "numerator": null,
                          "octave": 0,
                          "pitch_code": "N4s",
                          "value": "M"
                        }
                      }
                    ],
                    "id": "9b6fb5a9-9336-415b-bdc2-ca6442e90fa2",
                    "is_tuplet": null,
                    "tied_to_previous": null,
                    "total_duration": null,
                    "tuplet_ratio": null,
                    "value": null
                  }
                }
              ],
              "value": "S R G M"
            }
          }
        ],
        "notation_system": "Sargam",
        "value": "S R G M"
      }
    }
  ],
  "format_cache": {
    "lilypond": null,
    "midi": null,
    "music_text": "S R G M",
    "svg": null
  },
  "metadata": {
    "created_at": "2025-09-26T05:40:04.531Z",
    "created_by": "Web Interface",
    "title": "Untitled Document"
  },
  "timestamp": "2025-09-26T05:40:04.535050188+00:00",
  "ui_state": {
    "active_tab": "vexflow",
    "editor_mode": "text",
    "selection": {
      "cursor_position": 0,
      "cursor_uuid": null,
      "selected_uuids": []
    },
    "viewport": {
      "scroll_x": 0,
      "scroll_y": 0,
      "zoom_level": 1.0
    }
  },
  "version": "1.0.0"
}